amici/__init__.py
amici/_anndataloader.py
amici/_anntorchdataset.py
amici/_components.py
amici/_constants.py
amici/_model.py
amici/_module.py
amici/_utils.py
amici/_wandb_training_mixin.py
amici/_wandb_trainrunner.py
amici/callbacks/__init__.py
amici/callbacks/_callbacks.py
amici/interpretation/__init__.py
amici/interpretation/_ablation_module.py
amici/interpretation/_attention_module.py
amici/interpretation/_counterfactual_attention_module.py
amici/interpretation/_explained_variance_module.py
amici/interpretation/_utils.py
amici/tools/__init__.py
amici/tools/_data_utils.py
amici_st-0.1.0.dist-info/METADATA
amici_st-0.1.0.dist-info/WHEEL
amici_st-0.1.0.dist-info/licenses/LICENSE
amici_st-0.1.0.dist-info/RECORD
