Metadata-Version: 2.4
Name: amici-st
Version: 0.1.0
Summary: Cross-attention-based cell-cell interaction inference from ST data.
Project-URL: Source, https://github.com/azizilab/amici
Project-URL: Home-page, https://github.com/azizilab/amici
Author: Justin Hong, Khushi Desai
Maintainer-email: Justin Hong <justin.hong@columbia.edu>, Khushi Desai <kpd2137@gmail.com>
License: Attribution-NonCommercial 4.0 International
License-File: LICENSE
Requires-Python: >=3.10
Requires-Dist: anndata
Requires-Dist: einops
Requires-Dist: jax==0.4.23
Requires-Dist: jaxlib==0.4.23
Requires-Dist: matplotlib
Requires-Dist: numpy
Requires-Dist: openchord
Requires-Dist: pooch
Requires-Dist: pytest
Requires-Dist: scanpy
Requires-Dist: scikit-learn
Requires-Dist: scipy<=1.12.0
Requires-Dist: scvi-tools==1.2.2
Requires-Dist: seaborn
Requires-Dist: session-info
Requires-Dist: transformer-lens==1.14.0
Requires-Dist: typeguard
Requires-Dist: wandb
Requires-Dist: xarray
Provides-Extra: dev
Requires-Dist: pre-commit; extra == 'dev'
Requires-Dist: twine>=4.0.2; extra == 'dev'
Provides-Extra: doc
Requires-Dist: docutils!=0.18.*,!=0.19.*,>=0.8; extra == 'doc'
Requires-Dist: ipykernel; extra == 'doc'
Requires-Dist: ipython; extra == 'doc'
Requires-Dist: myst-nb; extra == 'doc'
Requires-Dist: pandas; extra == 'doc'
Requires-Dist: sphinx-autodoc-typehints; extra == 'doc'
Requires-Dist: sphinx-book-theme>=1.0.0; extra == 'doc'
Requires-Dist: sphinx-copybutton; extra == 'doc'
Requires-Dist: sphinx>=4; extra == 'doc'
Requires-Dist: sphinxcontrib-bibtex>=1.0.0; extra == 'doc'
Requires-Dist: sphinxext-opengraph; extra == 'doc'
Provides-Extra: test
Requires-Dist: coverage; extra == 'test'
